Metadata-Version: 2.1
Name: solarcurtailment
Version: 1.0.0
Summary: Analyze solar curtailment of a certain site in a certain date
Author-email: "Naomi Stringer, Baran Yildiz, Timothy Klymenko, M. Syahman Samhan" <m.samhan@student.unsw.edu.au>
License: MIT License
Project-URL: repository, https://github.com/mssamhan31/Solar-Curtailment
Project-URL: documentation, https://github.com/mssamhan31/Solar-Curtailment#readme
Keywords: solar,curtailment,tripping,vvar,vwatt,voltage,power
Classifier: License :: OSI Approved :: MIT License
Classifier: Programming Language :: Python
Classifier: Programming Language :: Python :: 3
Requires-Python: >=3.7
License-File: LICENSE.md
